<?xml version="1.0" encoding="UTF-8"?>
<databaseChangeLog
        xmlns="http://www.liquibase.org/xml/ns/dbchangelog"
        xmlns:xsi="http://www.w3.org/2001/XMLSchema-instance"
        xsi:schemaLocation="http://www.liquibase.org/xml/ns/dbchangelog
                      http://www.liquibase.org/xml/ns/dbchangelog/dbchangelog-latest.xsd"
        objectQuotingStrategy="QUOTE_ONLY_RESERVED_WORDS">

    <changeSet id="1" author="timesheets">
        <!-- Haulmont -->
        <insert tableName="TS_CLIENT" dbms="postgresql, mssql, hsqldb">
            <column name="ID" value="70b81d7f-3f91-efb0-bede-ccaa3741683d"/>
            <column name="NAME" value="Haulmont"/>
            <column name="CONTACT_INFORMATION_ADDRESS" value="UK, London, Labs House, 15-19 Bloomsbury Way, WC1A 2TH"/>
            <column name="CONTACT_INFORMATION_EMAIL" value="info@haulmont.com"/>
            <column name="CONTACT_INFORMATION_PHONE" value="+44 (0) 20 3214 5110"/>
            <column name="CONTACT_INFORMATION_URL" value="https://haulmont.tech/"/>
            <column name="VERSION" value="1"/>
        </insert>

        <insert tableName="TS_CLIENT" dbms="oracle, mysql, mariadb">
            <column name="ID" value="70b81d7f3f91efb0bedeccaa3741683d"/>
            <column name="NAME" value="Haulmont"/>
            <column name="CONTACT_INFORMATION_ADDRESS" value="UK, London, Labs House, 15-19 Bloomsbury Way, WC1A 2TH"/>
            <column name="CONTACT_INFORMATION_EMAIL" value="info@haulmont.com"/>
            <column name="CONTACT_INFORMATION_PHONE" value="+44 (0) 20 3214 5110"/>
            <column name="CONTACT_INFORMATION_URL" value="https://haulmont.tech/"/>
            <column name="VERSION" value="1"/>
        </insert>

        <!-- John Doe -->
        <insert tableName="TS_CLIENT" dbms="postgresql, mssql, hsqldb">
            <column name="ID" value="f132ddf1-e3dc-b587-1279-008599d37c93"/>
            <column name="NAME" value="John Doe"/>
            <column name="CONTACT_INFORMATION_ADDRESS" value="Lorem ipsum dolor sit amet, consectetur adipiscing elit, sed do eiusmod tempor incididunt ut labore et dolore magna aliqua. Ut enim ad minim veniam, quis nostrud exercitation ullamco laboris nisi ut aliquip ex ea commodo consequat."/>
            <column name="CONTACT_INFORMATION_EMAIL" value="info@example.com"/>
            <column name="CONTACT_INFORMATION_PHONE" value="+9876543210"/>
            <column name="CONTACT_INFORMATION_URL" value="https://example.com/"/>
            <column name="VERSION" value="1"/>
        </insert>

        <insert tableName="TS_CLIENT" dbms="oracle, mysql, mariadb">
            <column name="ID" value="f132ddf1e3dcb5871279008599d37c93"/>
            <column name="NAME" value="John Doe"/>
            <column name="CONTACT_INFORMATION_ADDRESS" value="Lorem ipsum dolor sit amet, consectetur adipiscing elit, sed do eiusmod tempor incididunt ut labore et dolore magna aliqua. Ut enim ad minim veniam, quis nostrud exercitation ullamco laboris nisi ut aliquip ex ea commodo consequat."/>
            <column name="CONTACT_INFORMATION_EMAIL" value="info@example.com"/>
            <column name="CONTACT_INFORMATION_PHONE" value="+9876543210"/>
            <column name="CONTACT_INFORMATION_URL" value="https://example.com/"/>
            <column name="VERSION" value="1"/>
        </insert>

        <!-- My Company -->
        <insert tableName="TS_CLIENT" dbms="postgresql, mssql, hsqldb">
            <column name="ID" value="1d5782f3-f084-3287-035f-7a30a210ff02"/>
            <column name="NAME" value="My Company"/>
            <column name="CONTACT_INFORMATION_ADDRESS" value="Lorem ipsum dolor sit amet, consectetur adipiscing elit, sed do eiusmod tempor incididunt ut labore et dolore magna aliqua. Ut enim ad minim veniam, quis nostrud exercitation ullamco laboris nisi ut aliquip ex ea commodo consequat."/>
            <column name="CONTACT_INFORMATION_EMAIL" value="info@company.com"/>
            <column name="CONTACT_INFORMATION_PHONE" value="+1234567890"/>
            <column name="VERSION" value="1"/>
        </insert>

        <insert tableName="TS_CLIENT" dbms="oracle, mysql, mariadb">
            <column name="ID" value="1d5782f3f0843287035f7a30a210ff02"/>
            <column name="NAME" value="My Company"/>
            <column name="CONTACT_INFORMATION_ADDRESS" value="Lorem ipsum dolor sit amet, consectetur adipiscing elit, sed do eiusmod tempor incididunt ut labore et dolore magna aliqua. Ut enim ad minim veniam, quis nostrud exercitation ullamco laboris nisi ut aliquip ex ea commodo consequat."/>
            <column name="CONTACT_INFORMATION_EMAIL" value="info@company.com"/>
            <column name="CONTACT_INFORMATION_PHONE" value="+1234567890"/>
            <column name="VERSION" value="1"/>
        </insert>
    </changeSet>
</databaseChangeLog>